atlas_meshtastic_bridge/__init__.py
atlas_meshtastic_bridge/cli.py
atlas_meshtastic_bridge/client.py
atlas_meshtastic_bridge/config.py
atlas_meshtastic_bridge/dedupe.py
atlas_meshtastic_bridge/gateway.py
atlas_meshtastic_bridge/message.py
atlas_meshtastic_bridge/metrics.py
atlas_meshtastic_bridge/reassembly.py
atlas_meshtastic_bridge/spool.py
atlas_meshtastic_bridge/transport.py
atlas_meshtastic_bridge/modes/__init__.py
atlas_meshtastic_bridge/modes/general.json
atlas_meshtastic_bridge/operations/__init__.py
atlas_meshtastic_bridge/operations/_echo.py
atlas_meshtastic_bridge/operations/get_changed_since.py
atlas_meshtastic_bridge/operations/get_full_dataset.py
atlas_meshtastic_bridge/operations/health.py
atlas_meshtastic_bridge/operations/entities/checkin_entity.py
atlas_meshtastic_bridge/operations/entities/create_entity.py
atlas_meshtastic_bridge/operations/entities/delete_entity.py
atlas_meshtastic_bridge/operations/entities/get_entity.py
atlas_meshtastic_bridge/operations/entities/get_entity_by_alias.py
atlas_meshtastic_bridge/operations/entities/list_entities.py
atlas_meshtastic_bridge/operations/entities/update_entity.py
atlas_meshtastic_bridge/operations/entities/update_entity_telemetry.py
atlas_meshtastic_bridge/operations/objects/add_object_reference.py
atlas_meshtastic_bridge/operations/objects/cleanup_object_references.py
atlas_meshtastic_bridge/operations/objects/create_object.py
atlas_meshtastic_bridge/operations/objects/delete_object.py
atlas_meshtastic_bridge/operations/objects/find_orphaned_objects.py
atlas_meshtastic_bridge/operations/objects/get_object.py
atlas_meshtastic_bridge/operations/objects/get_object_references.py
atlas_meshtastic_bridge/operations/objects/get_objects_by_entity.py
atlas_meshtastic_bridge/operations/objects/get_objects_by_task.py
atlas_meshtastic_bridge/operations/objects/list_objects.py
atlas_meshtastic_bridge/operations/objects/remove_object_reference.py
atlas_meshtastic_bridge/operations/objects/update_object.py
atlas_meshtastic_bridge-0.1.9.dist-info/METADATA
atlas_meshtastic_bridge-0.1.9.dist-info/WHEEL
atlas_meshtastic_bridge-0.1.9.dist-info/top_level.txt
atlas_meshtastic_bridge-0.1.9.dist-info/RECORD
