Metadata-Version: 2.4
Name: atlas-meshtastic-bridge
Version: 0.1.9
Summary: Reliable offline bridge for Atlas Command over Meshtastic radios.
Author: ATLAS Team
License-Expression: MIT
Project-URL: Homepage, https://github.com/the-Drunken-coder/ATLAS
Project-URL: Repository, https://github.com/the-Drunken-coder/ATLAS
Keywords: atlas,meshtastic,bridge,mesh,telemetry
Classifier: Development Status :: 3 - Alpha
Classifier: Intended Audience :: Developers
Classifier: Programming Language :: Python :: 3
Classifier: Programming Language :: Python :: 3.10
Classifier: Programming Language :: Python :: 3.11
Classifier: Programming Language :: Python :: 3.12
Classifier: Programming Language :: Python :: 3.13
Classifier: Topic :: Communications
Classifier: Topic :: Software Development :: Libraries
Requires-Python: >=3.10
Requires-Dist: atlas-asset-client>=0.3.0
Requires-Dist: msgpack>=1.0.7
Requires-Dist: zstandard>=0.22.0
Provides-Extra: meshtastic
Requires-Dist: meshtastic>=2.3.0; extra == "meshtastic"
Requires-Dist: pypubsub>=4.0.3; extra == "meshtastic"
Provides-Extra: dev
Requires-Dist: pytest>=7.0.0; extra == "dev"
Requires-Dist: pytest-cov>=4.0.0; extra == "dev"
